powerline_kubernetes/__init__.py
powerline_kubernetes/segments.py
powerline_kubernetes-1.2.0.dist-info/LICENSE
powerline_kubernetes-1.2.0.dist-info/METADATA
powerline_kubernetes-1.2.0.dist-info/WHEEL
powerline_kubernetes-1.2.0.dist-info/top_level.txt
powerline_kubernetes-1.2.0.dist-info/RECORD
