Metadata-Version: 2.1
Name: powerline-kubernetes
Version: 1.2.0
Summary: A Powerline segment to show Kubernetes context
Home-page: https://github.com/so0k/powerline-kubernetes
Author: Vincent De Smet
Author-email: vincent.drl@gmail.com
License: MIT
Keywords: powerline kubernetes context
Platform: UNKNOWN
Classifier: Environment :: Console
Classifier: Intended Audience :: Developers
Classifier: License :: OSI Approved :: MIT License
Classifier: Topic :: Terminals
Requires-Dist: powerline-status
Requires-Dist: kubernetes
